MANIFEST.in
README.rst
setup.cfg
setup.py
Lya_zelda/__init__.py
Lya_zelda/funcs.py
Lya_zelda.egg-info/PKG-INFO
Lya_zelda.egg-info/SOURCES.txt
Lya_zelda.egg-info/dependency_links.txt
Lya_zelda.egg-info/requires.txt
Lya_zelda.egg-info/top_level.txt
Lya_zelda/DATA/List_of_DATA_files
Lya_zelda/DATA/nn_INFLOWS_N_2500000_Npix_1000_Dl_-18.5_18.5_Dc_True_nor_False_sca_True_256_256_256_256_256_it_1.sav
Lya_zelda/DATA/nn_OUTFLOW_N_2500000_Npix_1000_Dl_-18.5_18.5_Dc_True_nor_False_sca_True_256_256_256_256_256_it_1.sav