Metadata-Version: 2.1
Name: Lya-zelda
Version: 0.0.5
Summary: Fast Lyman alpha Radiative Transfer for everyone!
Home-page: https://github.com/sidgurun/LyaRT-Grid
Author: Siddhartha Gurung Lopez
Author-email: gurung.lopez@gmail.com
License: UNKNOWN
Download-URL: https://github.com/sidgurun/Lya_zelda/archive/refs/tags/0.0.05.tar.gz
Platform: UNKNOWN
Classifier: Programming Language :: Python :: 3
Classifier: License :: OSI Approved :: MIT License
Classifier: Operating System :: OS Independent
